{
   "teamCountTotal": 36,
   "teamCountPage": 36,
   "pageCurrent": 1,
   "pageTotal": 1,
   "teams": [
      {
         "teamNumber": 100,
         "nameFull": "Salesky.dev/Viasat/Dome Construction/Gene Haas Foundation/Boeing/Pacific Gas and Electric/Lockheed Martin/Alan Steel and Supply Company/Amgen/Intuative Foundation/PG&E/Woodside High School&Woodside High School",
         "nameShort": "The Wildhats",
         "city": "Woodside",
         "stateProv": "California",
         "country": "USA",
         "rookieYear": 1995,
         "robotName": "",
         "districtCode": null,
         "schoolName": "Woodside High School",
         "website": "",
         "homeCMP": "CMPTX"
      },
      {
         "teamNumber": 115,
         "nameFull": "Fremont Union High School Foundation/Qualcomm/Intuitive Surgical/Abbott Fund/Western Digital/ARM/Bishop-Wisecarver/Google/Monta Vista High School/Zoox/TE Connectivity/Paypal/Costco/Intel/Autodesk/Rotary International/BAE/NASA&Monta Vista High School",
         "nameShort": "MVRT",
         "city": "Cupertino",
         "stateProv": "California",
         "country": "USA",
         "rookieYear": 1998,
         "robotName": "",
         "districtCode": null,
         "schoolName": "Monta Vista High School",
         "website": "",
         "homeCMP": "CMPTX"
      },
      {
         "teamNumber": 253,
         "nameFull": "Caccia Plumbing Inc/Millbrae Lions Club/Bishop Wisecarver/San Mateo Union High School District/Google/FIRST NorCal/Lockheed Martin/Santosh Abraham/SolidWorks/Comcast NBCUniversal/GATE/Intuitive Foundation/Millbrae Leos Club/San Carlos Kiwanis Club/Upward Credit Union/AGC Acupuncture Clinic/Rotary Club of Millbrae/Millbrae T4U/Tea Link/San Mateo Credit Union/Numis International Inc&Mills High School",
         "nameShort": "Boba Bots",
         "city": "Millbrae",
         "stateProv": "California",
         "country": "USA",
         "rookieYear": 1999,
         "robotName": "",
         "districtCode": null,
         "schoolName": "Mills High School",
         "website": "",
         "homeCMP": "CMPTX"
      },
      {
         "teamNumber": 604,
         "nameFull": "Leland High School FRC Team 604 Quixilver/Apple/Society of Women Engineers/BAE Systems/Gene Haas Foundation/Intuitive Surgical Foundation/West Coast Products/Lockheed Martin/Leland Bridge/Qualcomm/NorCal FIRST/PGE/Almaden Valley Women's Club/604 Alumni and Parents/In-Kind: Hurricane Electric Internet Services-SolidWorks-OnShape&Leland High School",
         "nameShort": "Quixilver",
         "city": "San Jose",
         "stateProv": "California",
         "country": "USA",
         "rookieYear": 2001,
         "robotName": "",
         "districtCode": null,
         "schoolName": "Leland High School",
         "website": "",
         "homeCMP": "CMPTX"
      },
      {
         "teamNumber": 649,
         "nameFull": "KLA/Micron/Qualcomm/MSET Families & Friends/Trial & Error Robotics/Intuitive Surgical/Gorman Group/PG&E/Rotary Club of Saratoga/SolidWorks/GrabCAD&Saratoga High School",
         "nameShort": "MSET Fish",
         "city": "Saratoga",
         "stateProv": "California",
         "country": "USA",
         "rookieYear": 2001,
         "robotName": "",
         "districtCode": null,
         "schoolName": "Saratoga High School",
         "website": "",
         "homeCMP": "CMPTX"
      },
      {
         "teamNumber": 668,
         "nameFull": "Gilbert-Greenstein Family/KLA- Foundation/BAE/Qualcomm/Intuitive Foundation/Lockheed Martin/Pacific Gas & Electric Co./FIRST NorCal&Pioneer High School&Family/Community",
         "nameShort": "The Apes of Wrath",
         "city": "San Jose",
         "stateProv": "California",
         "country": "USA",
         "rookieYear": 2001,
         "robotName": "",
         "districtCode": null,
         "schoolName": "Family/Community & Pioneer High School",
         "website": "",
         "homeCMP": "CMPTX"
      },
      {
         "teamNumber": 852,
         "nameFull": "Intuitive/Norcal Robotics&Athenian School",
         "nameShort": "Acropolis Robotics",
         "city": "Danville",
         "stateProv": "California",
         "country": "USA",
         "rookieYear": 2002,
         "robotName": "",
         "districtCode": null,
         "schoolName": "Athenian School",
         "website": "",
         "homeCMP": "CMPTX"
      },
      {
         "teamNumber": 971,
         "nameFull": "NASA/Blue River Technologies/Google/John Deere/Plug and Play Information Technology/Mountain View High School PTSA/Intuitive Foundation/West Coast Products/InOrbit/PG&E/Dream Maker Fund/eBay&Mountain View High School",
         "nameShort": "Spartan Robotics",
         "city": "Mountain View",
         "stateProv": "California",
         "country": "USA",
         "rookieYear": 2002,
         "robotName": "",
         "districtCode": null,
         "schoolName": "Mountain View High School",
         "website": "",
         "homeCMP": "CMPTX"
      },
      {
         "teamNumber": 1072,
         "nameFull": "Harker Foundation/KeyShot/Alan Steel/Ozzy Boards/AutomationDirect/Destiny Tool/Right Question/Google/ThinBit & Harker Upper School",
         "nameShort": "Harker Robotics",
         "city": "San Jose",
         "stateProv": "California",
         "country": "USA",
         "rookieYear": 2003,
         "robotName": "",
         "districtCode": null,
         "schoolName": "Harker Upper School",
         "website": "",
         "homeCMP": "CMPTX"
      },
      {
         "teamNumber": 1280,
         "nameFull": "SRVEF/Parents of 1280 & San Ramon Valley High School",
         "nameShort": "Ragin' C-Biscuits",
         "city": "Danville",
         "stateProv": "California",
         "country": "USA",
         "rookieYear": 2004,
         "robotName": "",
         "districtCode": null,
         "schoolName": "San Ramon Valley High School",
         "website": "",
         "homeCMP": "CMPTX"
      },
      {
         "teamNumber": 1323,
         "nameFull": "Madera Unified School District/WestCoast Products/JBT FoodTech/PG&E/GBS Hardware/Evening Lions/Madera Fair/Kiwani's Madera/BK Lighting/BOEING&Madera High School",
         "nameShort": "MadTown Robotics",
         "city": "Madera",
         "stateProv": "California",
         "country": "USA",
         "rookieYear": 2004,
         "robotName": "",
         "districtCode": null,
         "schoolName": "Madera High School",
         "website": "",
         "homeCMP": "CMPTX"
      },
      {
         "teamNumber": 2035,
         "nameFull": "Big Sur International Marathon Foundation/Carmel Patent Agency/Mikenmare/Laptop Schools.org/Carmel Unified School District/Ryan Ranch Dental Care&Carmel High School",
         "nameShort": "Rockin' Bots",
         "city": "Carmel",
         "stateProv": "California",
         "country": "USA",
         "rookieYear": 2007,
         "robotName": "",
         "districtCode": null,
         "schoolName": "Carmel High School",
         "website": "",
         "homeCMP": "CMPTX"
      },
      {
         "teamNumber": 2135,
         "nameFull": "Gene Haas Foundation/Intuitive Foundation/Qualcomm/PG&E/FIRST Norcal/Mastercam/Dassault  Systemes/Spray Technology/Ansari Family/Chen Family&Presentation High School",
         "nameShort": "Presentation Invasion",
         "city": "San Jose",
         "stateProv": "California",
         "country": "USA",
         "rookieYear": 2007,
         "robotName": "",
         "districtCode": null,
         "schoolName": "Presentation High School",
         "website": "",
         "homeCMP": "CMPTX"
      },
      {
         "teamNumber": 2473,
         "nameFull": "Lockheed Martin/Intuitive Surgical/FUHSD Foundation/Advance Welding/Dave Izant/Johnson & Johnson/Apple/Gene Haas Foundation&Cupertino High School",
         "nameShort": "Goldstrikers",
         "city": "Cupertino",
         "stateProv": "California",
         "country": "USA",
         "rookieYear": 2008,
         "robotName": "",
         "districtCode": null,
         "schoolName": "Cupertino High School",
         "website": "",
         "homeCMP": "CMPTX"
      },
      {
         "teamNumber": 2643,
         "nameFull": "Apple/ARM/Lockheed Martin/Intuitive Surgical, Inc./Solid Works/Starbucks/Nob Hill&Santa Teresa High School",
         "nameShort": "Dark Matter",
         "city": "San Jose",
         "stateProv": "California",
         "country": "USA",
         "rookieYear": 2008,
         "robotName": "",
         "districtCode": null,
         "schoolName": "Santa Teresa High School",
         "website": "",
         "homeCMP": "CMPTX"
      },
      {
         "teamNumber": 3045,
         "nameFull": "&Junipero Serra High School",
         "nameShort": "Gear Gremlins",
         "city": "San Mateo",
         "stateProv": "California",
         "country": "USA",
         "rookieYear": 2009,
         "robotName": "",
         "districtCode": null,
         "schoolName": "Junipero Serra High School",
         "website": "",
         "homeCMP": "CMPTX"
      },
      {
         "teamNumber": 3257,
         "nameFull": "Bosch Semiconductor/Love of Learning/Stemp Labs/Oracle/Google&4-H",
         "nameShort": "Vortechs",
         "city": "Rocklin",
         "stateProv": "California",
         "country": "USA",
         "rookieYear": 2010,
         "robotName": "",
         "districtCode": null,
         "schoolName": "4-H",
         "website": "",
         "homeCMP": "CMPTX"
      },
      {
         "teamNumber": 3669,
         "nameFull": "Ram Mechanical/Ripon Christian Schools/Composite Envisions/Kamper Fabrication&Ripon Christian",
         "nameShort": "CarbonKnights",
         "city": "Ripon",
         "stateProv": "California",
         "country": "USA",
         "rookieYear": 2011,
         "robotName": "",
         "districtCode": null,
         "schoolName": "Ripon Christian",
         "website": "",
         "homeCMP": "CMPTX"
      },
      {
         "teamNumber": 4135,
         "nameFull": "Modesto City Schools/Boyett Make Dreams Real/NASA/Ayera Technology/Raymus Foundation/Hogan Manufacturing/Bright Homes/Gene Haas Foundation/Kitchen Crate/Jack Polkinghorne/Switzer Family/Port of Stockton&Fred C Beyer High School",
         "nameShort": "Iron Patriots",
         "city": "Modesto",
         "stateProv": "California",
         "country": "USA",
         "rookieYear": 2012,
         "robotName": "",
         "districtCode": null,
         "schoolName": "Fred C Beyer High School",
         "website": "",
         "homeCMP": "CMPTX"
      },
      {
         "teamNumber": 4171,
         "nameFull": "Qualcomm/Monterey Peninsula Unified School District/The Boeing Company/BAE/Intuitive Foundation/PG&E&Seaside High School",
         "nameShort": "BayBots",
         "city": "Seaside",
         "stateProv": "California",
         "country": "USA",
         "rookieYear": 2012,
         "robotName": "",
         "districtCode": null,
         "schoolName": "Seaside High School",
         "website": "",
         "homeCMP": "CMPTX"
      },
      {
         "teamNumber": 4255,
         "nameFull": "Naval Postgraduate School/Monterey High School Robotics/Monterey Peninsula Unified&Monterey High School",
         "nameShort": "Robodores",
         "city": "Monterey",
         "stateProv": "California",
         "country": "USA",
         "rookieYear": 2012,
         "robotName": "",
         "districtCode": null,
         "schoolName": "Monterey High School",
         "website": "",
         "homeCMP": "CMPTX"
      },
      {
         "teamNumber": 4765,
         "nameFull": "Solidworks/The Oelschig Family/The Ting Family&Pinewood School",
         "nameShort": "PWRUP",
         "city": "Los Altos Hills",
         "stateProv": "California",
         "country": "USA",
         "rookieYear": 2013,
         "robotName": "",
         "districtCode": null,
         "schoolName": "Pinewood School",
         "website": "",
         "homeCMP": "CMPTX"
      },
      {
         "teamNumber": 5089,
         "nameFull": "NASA/Boeing/Los Angeles Unified School District/Raytheon Technologies/Gene HASS Foundation/Los Angeles City College &Benjamin Franklin High School",
         "nameShort": "Robo-Nerds",
         "city": "Los Angeles",
         "stateProv": "California",
         "country": "USA",
         "rookieYear": 2014,
         "robotName": "",
         "districtCode": null,
         "schoolName": "Benjamin Franklin High School",
         "website": "",
         "homeCMP": "CMPTX"
      },
      {
         "teamNumber": 5104,
         "nameFull": "Microsoft/Apple/Yellow Brick Road/Whitson Engineers/Gene Haas Foundation/Advantech/Big Sur International Marathon Foundation/Intuitive Foundation/Qualcomm/PG&E Dream Maker/Ian Williams/Roberta Hunter/PGUSD&Pacific Grove High School",
         "nameShort": "BreakerBots",
         "city": "Pacific Grove",
         "stateProv": "California",
         "country": "USA",
         "rookieYear": 2014,
         "robotName": "",
         "districtCode": null,
         "schoolName": "Pacific Grove High School",
         "website": "",
         "homeCMP": "CMPTX"
      },
      {
         "teamNumber": 5171,
         "nameFull": "Naval Postgraduate School/DoD STEM Grant/FIRST NorCal/Argosy Foundation&York School",
         "nameShort": "Deus Ex Machina",
         "city": "Monterey",
         "stateProv": "California",
         "country": "USA",
         "rookieYear": 2014,
         "robotName": "",
         "districtCode": null,
         "schoolName": "York School",
         "website": "",
         "homeCMP": "CMPTX"
      },
      {
         "teamNumber": 5700,
         "nameFull": "FIRST NorCal/Gelest/GGI Carpet/FRC Team 4159 Cardinalbotics (2023) /FOSOTA/Qualcomm/NASA/NorCal (Anonymous)/Ruth Asawa SOTA/Macy's/Google/Carbon/Amazon/Intuitive Foundation&Ruth Asawa Sota High School&The Academy-San Francisco",
         "nameShort": "SOTA Cyberdragons",
         "city": "San Francisco",
         "stateProv": "California",
         "country": "USA",
         "rookieYear": 2015,
         "robotName": "",
         "districtCode": null,
         "schoolName": "The Academy-San Francisco & Ruth Asawa Sota High School",
         "website": "",
         "homeCMP": "CMPTX"
      },
      {
         "teamNumber": 6506,
         "nameFull": "PG&E Foundation / Dream Maker Fund/Qualcomm/Argosy Foundation & Salinas High School",
         "nameShort": "Steel Boot",
         "city": "Salinas",
         "stateProv": "California",
         "country": "USA",
         "rookieYear": 2017,
         "robotName": "",
         "districtCode": null,
         "schoolName": "Salinas High School",
         "website": "",
         "homeCMP": "CMPTX"
      },
      {
         "teamNumber": 6665,
         "nameFull": "Santa Catalina School",
         "nameShort": "C-Otters",
         "city": "Monterey",
         "stateProv": "California",
         "country": "USA",
         "rookieYear": 2017,
         "robotName": "",
         "districtCode": null,
         "schoolName": "Santa Catalina School",
         "website": "",
         "homeCMP": "CMPTX"
      },
      {
         "teamNumber": 6884,
         "nameFull": "San Benito High School District/American Electrical Service/Central Electric Company/Pride Conveyance Systems/Gibson Farms/Apple/Qualcomm/Marich Confectionary/Infinity Staffing Service/Blue River Technology/Ehn Family Fund Fidelity Charity/Prather Ranch/Tanimura & Antle Inc/Pacific Gas & Electric Company/Graniterock/Gene Haas Foundation/McKinnon Lumber/OSI Engineering Inc/Connectado/Marcus Building Systems Inc/Corbin/Central California/Team Families&San Benito High School",
         "nameShort": "Deep-Space Robotics",
         "city": "Hollister",
         "stateProv": "California",
         "country": "USA",
         "rookieYear": 2018,
         "robotName": "",
         "districtCode": null,
         "schoolName": "San Benito High School",
         "website": "",
         "homeCMP": "CMPTX"
      },
      {
         "teamNumber": 6918,
         "nameFull": "Napa County Office of Education/Syar Foundation/FJ Zimmerman Foundation/Chevron Corporation/Collins Aerospace/Intuitive (Surgical Robotics)/Chico Nut Company/Fastenal/State Farm Insurance/Napa Electric/Infinity Bottling/Napa Rotary/McCollum General Engineering/Mark Scott Construction/Benchmark Civil Construction, Inc./STEM Academy/Hop Creek Pub/Carls Jr./Friends & Family of Team 6918&Napa High School",
         "nameShort": "Napa Cellar Rats",
         "city": "Napa",
         "stateProv": "California",
         "country": "USA",
         "rookieYear": 2018,
         "robotName": "",
         "districtCode": null,
         "schoolName": "Napa High School",
         "website": "",
         "homeCMP": "CMPTX"
      },
      {
         "teamNumber": 6962,
         "nameFull": "POWERTEC/Global Logic/Apple/Intuitive Foundation/Lockheed Martin/SmugMug/Legion Technologies/General Catalyst/Khan Lab School Families/Gene Haas Foundation/Saints Capital&Khan Lab School",
         "nameShort": "Antares",
         "city": "Mountain View",
         "stateProv": "California",
         "country": "USA",
         "rookieYear": 2018,
         "robotName": "",
         "districtCode": null,
         "schoolName": "Khan Lab School",
         "website": "",
         "homeCMP": "CMPTX"
      },
      {
         "teamNumber": 7413,
         "nameFull": "Apple/Disney Enterprises, Inc./FIRST/DeWalt/FIPA/Gann Family/Herring Family/Lussier Family/Monterey Signs/Proud Source Water/Pizza My Heart&Family/Community",
         "nameShort": "Plus Ultra",
         "city": "Marina",
         "stateProv": "California",
         "country": "USA",
         "rookieYear": 2019,
         "robotName": "",
         "districtCode": null,
         "schoolName": "Family/Community",
         "website": "",
         "homeCMP": "CMPTX"
      },
      {
         "teamNumber": 7528,
         "nameFull": "NASA/Cisco/Applied Materials/IBM/The Law Offices of James A Ward/Silicon Valley Community Foundation&Live Oak High School",
         "nameShort": "Nuts and Bolts",
         "city": "Morgan Hill",
         "stateProv": "California",
         "country": "USA",
         "rookieYear": 2019,
         "robotName": "",
         "districtCode": null,
         "schoolName": "Live Oak High School",
         "website": "",
         "homeCMP": "CMPTX"
      },
      {
         "teamNumber": 7777,
         "nameFull": "Apple  Technology Company&Greenfield High School",
         "nameShort": "Septobots",
         "city": "Greenfield",
         "stateProv": "California",
         "country": "USA",
         "rookieYear": 2019,
         "robotName": "",
         "districtCode": null,
         "schoolName": "Greenfield High School",
         "website": "",
         "homeCMP": "CMPTX"
      },
      {
         "teamNumber": 9006,
         "nameFull": "Bay Area Muslim Scouting",
         "nameShort": "Crescent Wing Robotics",
         "city": "San Jose",
         "stateProv": "California",
         "country": "USA",
         "rookieYear": 2023,
         "robotName": "",
         "districtCode": null,
         "schoolName": "Bay Area Muslim Scouting",
         "website": "",
         "homeCMP": "CMPTX"
      },
      {
         "teamNumber": 9546,
         "nameFull": "Oberoi International School/Incertech/Electronics Bazaar/Whistling Woods International/Sparkel Diamonds&Oberoi International School - OGC Campus",
         "nameShort": "TechnoLeopards",
         "city": "Mumbai",
         "stateProv": "Maharashtra",
         "country": "India",
         "rookieYear": 2024,
         "robotName": "",
         "districtCode": null,
         "schoolName": "Oberoi International School - OGC Campus",
         "website": "",
         "homeCMP": "CMPTX"
      }
   ]
}